{
  "app": {
    "title": "Lorerim GigaPlanner Plus",
    "subtitle": "Character Build Planner",
    "versionLabel": "Modpack Version",
    "footer": "Unofficial fan tool for the LoreRim Skyrim modpack. Not affiliated with LoreRim."
  },
  "nav": {
    "home": "Home",
    "planner": "Planner",
    "builds": "My Builds"
  },
  "landing": {
    "eyebrow": "LoreRim Build Planner",
    "headline": "Plan your character before you enter Skyrim",
    "description": "Pick your race, stone, blessing, traits, and perks — then save multiple builds locally in your browser and share them with a code.",
    "cta": "Open Planner",
    "ctaHint": "No account required. Builds auto-save in your browser.",
    "feature1Title": "Character Setup",
    "feature1Description": "Configure race, standing stone, blessing, traits, and major/minor skills with live validation against LoreRim rules.",
    "feature2Title": "Interactive Skill Trees",
    "feature2Description": "Browse and select perks with prerequisite checks, skill requirements, and tooltips driven by game data.",
    "feature3Title": "Multiple Saved Builds",
    "feature3Description": "Create, rename, switch, and delete builds. Everything saves automatically in local storage.",
    "feature4Title": "Shareable Build Codes",
    "feature4Description": "Copy a compact build code or load one from a link to recreate a character plan instantly."
  },
  "planner": {
    "intro": "Configure your build below. Changes save automatically to the active build slot."
  },
  "level-bar": {
    "playerLevel": "Level",
    "perkPointsRemaining": "Perk points remaining",
    "perkPointsSpent": "spent",
    "perkPointsPerLevel": "{count} perk pt/level",
    "skillPointsRemaining": "Skill points remaining",
    "skillPointsSpent": "spent",
    "skillPointsPerLevel": "{count} skill pt/level",
    "overBudget": "over budget by {count}"
  },
  "panels": {
    "character-setup": {
      "title": "Character Setup",
      "race": "Race",
      "selectRace": "Select race...",
      "standingStone": "Standing Stone",
      "blessing": "Blessing",
      "traits": "Traits",
      "majorSkills": "Major Skills",
      "minorSkills": "Minor Skills",
      "majorRemaining": "Major skills remaining",
      "minorRemaining": "Minor skills remaining",
      "traitsRemaining": "Traits remaining",
      "remaining": "remaining",
      "selected": "Selected",
      "search": "Search...",
      "noMatches": "No matches",
      "noneSelected": "None selected",
      "backToOverview": "Overview",
      "backToPerks": "Perks",
      "baseStats": "Base Stats",
      "startingSkills": "Starting skills",
      "bonuses": "Bonuses",
      "health": "Health",
      "magicka": "Magicka",
      "stamina": "Stamina",
      "healthRegen": "Health Regeneration",
      "magickaRegen": "Magicka Regeneration",
      "staminaRegen": "Stamina Regeneration",
      "carryWeight": "Carry Weight",
      "unarmedDamage": "Unarmed Damage",
      "description": "Description",
      "shrineBonus": "Shrine",
      "followerBonus": "Follower",
      "devoteeBonus": "Devotee",
      "races": "Races",
      "startingRaces": "Starting races"
    },
    "attributes": {
      "title": "Attributes",
      "health": "Health",
      "magicka": "Magicka",
      "stamina": "Stamina",
      "remaining": "Attribute choices remaining"
    },
    "skill-trees": {
      "title": "Skill Trees",
      "resetSkill": "Reset this skill",
      "resetAll": "Reset ALL skills",
      "skillReq": "Skill requirement",
      "playerLevelReq": "Level requirement",
      "skillLevel": "Skill level",
      "skillLevelMin": "Min",
      "perksSelected": "perks selected",
      "locked": "Locked",
      "available": "Available",
      "selected": "Selected",
      "perkRank": "Rank",
      "nextRank": "Next rank",
      "upgradeAvailable": "Click to upgrade",
      "skillReqConflictDismiss": "Dismiss",
      "skillReqConflictSingle": "{perk} requires skill level {required}. Your skill level is now {current}, so it was removed.",
      "skillReqConflictMultiple": "{count} perks were removed because your skill level is now too low.",
      "skillReqConflictLegend": "Removed (skill too low)"
    },
    "derived-stats": {
      "title": "Derived Attributes"
    },
    "saved-builds": {
      "title": "Saved Builds",
      "autoSaveHint": "Changes save automatically in your browser",
      "newBuild": "New Build",
      "renameBuild": "Rename build",
      "deleteBuild": "Delete build",
      "saveRename": "Save name",
      "cancelRename": "Cancel rename",
      "lastSaved": "Last saved"
    },
    "build-library": {
      "eyebrow": "Build Library",
      "title": "My Builds",
      "subtitle": "Manage, share, import, and export your saved character builds.",
      "openPlanner": "Open Planner",
      "activeBadge": "Active",
      "buildCount": "{count} saved builds",
      "noRace": "No race selected",
      "perkCount": "{count} perks",
      "shareCodeTitle": "Share Codes",
      "shareCodeDescription": "Compact codes for sharing a build in chat, forums, or planner links.",
      "activeBuildCode": "Active build",
      "unnamedBuild": "Untitled build",
      "importCodeTitle": "Import a code",
      "importCodePlaceholder": "Paste code here...",
      "importAsNew": "Import as new",
      "importToActive": "Replace active",
      "backupTitle": "Backups",
      "backupDescription": "Save or restore builds as {extension} files on this device or another.",
      "backupExtension": ".gpp",
      "backupImportTitle": "Import backup",
      "chooseBackupFile": "Upload backup file",
      "backupExportTitle": "Export backup",
      "importedAsNew": "Build imported as a new slot.",
      "importedToActive": "Active build updated from code.",
      "importedLibrary": "Build library imported.",
      "importEmptyLibrary": "Library file contains no builds.",
      "savedBuildsTitle": "All Builds",
      "autoSaveHint": "click to select · drag handle to reorder",
      "dragToReorder": "Drag to reorder",
      "newBuild": "New Build",
      "renameBuild": "Rename",
      "deleteBuild": "Delete",
      "saveRename": "Save name",
      "cancelRename": "Cancel rename",
      "lastSaved": "Updated",
      "copyCode": "Copy code",
      "copiedCode": "Copied!",
      "copyLink": "Copy link",
      "copiedLink": "Link copied!",
      "exportBackup": "Export backup",
      "exportActive": "Active build",
      "exportAll": "Full library"
    },
    "build-summary": {
      "title": "Build Summary",
      "buildCode": "Build Code",
      "copyCode": "Click to copy",
      "copied": "Copied!",
      "description": "Description",
      "descriptionPlaceholder": "Notes about your build...",
      "resetBuild": "Reset Build",
      "loadFromCode": "Load from code"
    }
  },
  "errors": {
    "invalidBuildCode": "Invalid build code",
    "prerequisiteNotMet": "Prerequisite not met",
    "skillLimitReached": "Skill limit reached",
    "traitLimitReached": "Trait limit reached"
  }
}
